ee_metadata/__init__.py
ee_metadata/main.py
ee_metadata/primers.csv
ee_metadata-0.2.2.dist-info/LICENSE
ee_metadata-0.2.2.dist-info/METADATA
ee_metadata-0.2.2.dist-info/WHEEL
ee_metadata-0.2.2.dist-info/entry_points.txt
ee_metadata-0.2.2.dist-info/RECORD
