Metadata-Version: 2.3
Name: ee-metadata
Version: 0.2.2
Summary: A high-performance CLI tool from eDNA-Explorer to generate metadata from a directory of fastq files.
License: MIT
Keywords: bioinformatics,fastq,metadata,genomics,cli,edna
Author: Jim Jeffers
Author-email: jim@ednaexplorer.org
Requires-Python: >=3.9,<4.0
Classifier: Development Status :: 4 - Beta
Classifier: Environment :: Console
Classifier: Intended Audience :: Science/Research
Classifier: License :: OSI Approved :: MIT License
Classifier: Operating System :: OS Independent
Classifier: Programming Language :: Python :: 3
Classifier: Programming Language :: Python :: 3.9
Classifier: Programming Language :: Python :: 3.10
Classifier: Programming Language :: Python :: 3.11
Classifier: Programming Language :: Python :: 3.12
Classifier: Programming Language :: Python :: 3.13
Classifier: Topic :: Scientific/Engineering :: Bio-Informatics
Requires-Dist: polars (>=1.3.0,<2.0.0)
Requires-Dist: python-dateutil (>=2.8.2,<3.0.0)
Requires-Dist: rapidfuzz (>=3.6.0,<4.0.0)
Requires-Dist: rich (>=14.1.0,<15.0.0)
Requires-Dist: typer (>=0.16.0,<0.17.0)
Project-URL: Homepage, https://github.com/eDNA-Explorer/ee-metadata
Project-URL: Repository, https://github.com/eDNA-Explorer/ee-metadata
